sourceprotected/__init__.py
sourceprotected/cli.py
sourceprotected/codec.py
sourceprotected/py.typed
register_sourceprotected.pth
sourceprotected-0.1.0.dist-info/METADATA
sourceprotected-0.1.0.dist-info/WHEEL
sourceprotected-0.1.0.dist-info/entry_points.txt
sourceprotected-0.1.0.dist-info/licenses/LICENSE
sourceprotected-0.1.0.dist-info/RECORD
